pipeforce_sdk.py
pipeforce_sdk_python-10.0.46.dist-info/LICENSE
pipeforce_sdk_python-10.0.46.dist-info/METADATA
pipeforce_sdk_python-10.0.46.dist-info/WHEEL
pipeforce_sdk_python-10.0.46.dist-info/top_level.txt
pipeforce_sdk_python-10.0.46.dist-info/RECORD
