Metadata-Version: 2.1
Name: pipeforce-sdk-python
Version: 10.0.46
Summary: Python SDK for PIPEFORCE
Author: LOGABIT GmbH
Classifier: Programming Language :: Python :: 3
Classifier: License :: OSI Approved :: Apache Software License
Classifier: Operating System :: OS Independent
Requires-Python: >=3.9
License-File: LICENSE
